LICENSE
MANIFEST.in
README.md
requirements.txt
setup.cfg
setup.py
subtractAirglow/3x3_icon.webp
subtractAirglow/Airglow Template Data 8-21-2021.npy
subtractAirglow/AirglowRemovalUi.py
subtractAirglow/GUI.py
subtractAirglow/__init__.py
subtractAirglow/aa_LSFTable_G130M_1291_LP1_cn.dat
subtractAirglow/aa_LSFTable_G130M_1291_LP2_cn.dat
subtractAirglow/aa_LSFTable_G130M_1291_LP3_cn.dat
subtractAirglow/aa_LSFTable_G130M_1291_LP4_cn.dat
subtractAirglow/aa_LSFTable_G130M_1291_LP5_cn.dat
subtractAirglow/aa_LSFTable_G130M_1327_LP3_cn.dat
subtractAirglow/version.py
subtractAirglow/voigt.py
subtractAirglow.egg-info/PKG-INFO
subtractAirglow.egg-info/SOURCES.txt
subtractAirglow.egg-info/dependency_links.txt
subtractAirglow.egg-info/requires.txt
subtractAirglow.egg-info/top_level.txt