Metadata-Version: 2.1
Name: subtractAirglow
Version: 0.1.0.2
Summary: Subtract airglow and reconstruct stellar emission from COS G130M spectra
Home-page: https://github.com/AstroAguirre/subtractAirglow.git
Download-URL: https://github.com/AstroAguirre/subtractAirglow/archive/refs/tags/v0.1.0.2.tar.gz
Author: Fernando Cruz Aguirre
Author-email: edwinfernando-cruzaguirre@uiowa.edu
License: MIT
License-File: LICENSE
